setup.py
tmux_cssh/__init__.py
tmux_cssh/cli.py
tmux_cssh/main.py
tmux_cssh.egg-info/PKG-INFO
tmux_cssh.egg-info/SOURCES.txt
tmux_cssh.egg-info/dependency_links.txt
tmux_cssh.egg-info/entry_points.txt
tmux_cssh.egg-info/requires.txt
tmux_cssh.egg-info/top_level.txt