Metadata-Version: 1.0
Name: tmux-cssh
Version: 1.2.2
Summary: Simple script to provide cssh/ClusterSSH like functionality using only tmux
Home-page: https://github.com/cscutcher/tmux_cssh
Author: Chris Scutcher
Author-email: chris.scutcher@ninebysix.co.uk
License: UNKNOWN
Platform: UNKNOWN
